catalyst_sdwan_lab/__init__.py
catalyst_sdwan_lab/__main__.py
catalyst_sdwan_lab/cli.py
catalyst_sdwan_lab/data/certs/cacsr_details.txt
catalyst_sdwan_lab/data/certs/chainCA.pem
catalyst_sdwan_lab/data/certs/openssl-commands.md
catalyst_sdwan_lab/data/certs/rootCA.pem
catalyst_sdwan_lab/data/certs/rootCA.srl
catalyst_sdwan_lab/data/certs/rootca_details.txt
catalyst_sdwan_lab/data/certs/signCA.csr
catalyst_sdwan_lab/data/certs/signCA.key
catalyst_sdwan_lab/data/certs/signCA.pem
catalyst_sdwan_lab/data/certs/v3ext.cnf
catalyst_sdwan_lab/data/cml_lab_definition/backup/controller-cloud-init.j2
catalyst_sdwan_lab/data/cml_lab_definition/backup/edge-cloud-init.j2
catalyst_sdwan_lab/data/cml_lab_definition/backup/manager-cloud-init.j2
catalyst_sdwan_lab/data/cml_lab_definition/backup/sdrouting-cloud-init.j2
catalyst_sdwan_lab/data/cml_lab_definition/backup/validator-cloud-init.j2
catalyst_sdwan_lab/data/cml_lab_definition/deploy/cml-base-topology.j2
catalyst_sdwan_lab/data/cml_lab_definition/deploy/controller-cloud-init.j2
catalyst_sdwan_lab/data/cml_lab_definition/deploy/manager-cloud-init.j2
catalyst_sdwan_lab/data/cml_lab_definition/deploy/sdrouting-cloud-init.j2
catalyst_sdwan_lab/data/cml_lab_definition/deploy/validator-cloud-init.j2
catalyst_sdwan_lab/data/cml_nodes_definition/cat-sdwan-controller.yaml
catalyst_sdwan_lab/data/cml_nodes_definition/cat-sdwan-edge.yaml
catalyst_sdwan_lab/data/cml_nodes_definition/cat-sdwan-manager.yaml
catalyst_sdwan_lab/data/cml_nodes_definition/cat-sdwan-validator.yaml
catalyst_sdwan_lab/data/manager_configs/v1_ipdual/device_templates/template/Default_AWS_TGW_C8000V_Template_V01.json
catalyst_sdwan_lab/data/manager_configs/v1_ipdual/device_templates/template/Default_AWS_TGW_CSR1000V_Template_V01.json
catalyst_sdwan_lab/data/manager_configs/v1_ipdual/device_templates/template/Default_Azure_vWAN_C8000V_Template_V01.json
catalyst_sdwan_lab-2.1.6.dist-info/LICENSE
catalyst_sdwan_lab-2.1.6.dist-info/METADATA
catalyst_sdwan_lab-2.1.6.dist-info/WHEEL
catalyst_sdwan_lab-2.1.6.dist-info/entry_points.txt
catalyst_sdwan_lab-2.1.6.dist-info/RECORD
