Metadata-Version: 2.1
Name: catalyst-sdwan-lab
Version: 2.1.6
Summary: Catalyst SD-WAN Lab Deployment Tool - Automation Tool for managing Cisco Catalyst SD-WAN labs inside Cisco Modeling Labs
Home-page: https://github.com/cisco-open/sdwan-lab-deployment-tool
License: BSD-3-Clause
Keywords: cisco,catalyst,sdwan,lab
Author: Tomasz Zarski
Author-email: tzarski@cisco.com
Requires-Python: >=3.9.2,<4.0.0
Classifier: License :: OSI Approved :: BSD License
Classifier: Programming Language :: Python :: 3
Classifier: Programming Language :: Python :: 3.10
Classifier: Programming Language :: Python :: 3.11
Classifier: Programming Language :: Python :: 3.12
Requires-Dist: catalystwan (>=0.33.10,<0.34.0)
Requires-Dist: cisco-sdwan (==1.26)
Requires-Dist: click (>=8.1.7,<9.0.0)
Requires-Dist: jinja2 (>=3.1.6,<4.0.0)
Requires-Dist: passlib (>=1.7.4,<2.0.0)
Requires-Dist: pyats[full] (>=25.1)
Requires-Dist: pyopenssl (>=24.0.0,<25.0.0)
Requires-Dist: requests (>=2.28.1,<3.0.0)
Requires-Dist: rich-click (>=1.8.5,<2.0.0)
Requires-Dist: ruamel-yaml (>=0.17.21,<0.18.0)
Requires-Dist: urllib3 (>=1.26.18,<3.0.0)
Requires-Dist: virl2-client (>=2.8.0,<3.0.0)
Project-URL: Repository, https://github.com/cisco-open/sdwan-lab-deployment-tool
